LICENSE
MANIFEST.in
README.md
setup.py
lib/ansible/__init__.py
lib/ansible/module_utils/__init__.py
lib/ansible/module_utils/alicloud_ecs.py
lib/ansible/module_utils/alicloud_oss.py
lib/ansible/modules/__init__.py
lib/ansible/modules/cloud/__init__.py
lib/ansible/modules/cloud/alicloud/__init__.py
lib/ansible/modules/cloud/alicloud/_ali_disk_facts.py
lib/ansible/modules/cloud/alicloud/_ali_eip_facts.py
lib/ansible/modules/cloud/alicloud/_ali_eni_facts.py
lib/ansible/modules/cloud/alicloud/_ali_image_facts.py
lib/ansible/modules/cloud/alicloud/_ali_instance_facts.py
lib/ansible/modules/cloud/alicloud/_ali_oss_bucket_facts.py
lib/ansible/modules/cloud/alicloud/_ali_oss_object_facts.py
lib/ansible/modules/cloud/alicloud/_ali_rds_account_facts.py
lib/ansible/modules/cloud/alicloud/_ali_rds_instance_facts.py
lib/ansible/modules/cloud/alicloud/_ali_route_entry_facts.py
lib/ansible/modules/cloud/alicloud/_ali_security_group_facts.py
lib/ansible/modules/cloud/alicloud/_ali_slb_lb_facts.py
lib/ansible/modules/cloud/alicloud/_ali_slb_listener_facts.py
lib/ansible/modules/cloud/alicloud/_ali_slb_server_facts.py
lib/ansible/modules/cloud/alicloud/_ali_slb_vsg_facts.py
lib/ansible/modules/cloud/alicloud/_ali_vpc_facts.py
lib/ansible/modules/cloud/alicloud/_ali_vswitch_facts.py
lib/ansible/modules/cloud/alicloud/_alicloud_bucket.py
lib/ansible/modules/cloud/alicloud/_alicloud_bucket_object.py
lib/ansible/modules/cloud/alicloud/_alicloud_disk.py
lib/ansible/modules/cloud/alicloud/_alicloud_disk_facts.py
lib/ansible/modules/cloud/alicloud/_alicloud_eip.py
lib/ansible/modules/cloud/alicloud/_alicloud_ess_configuration.py
lib/ansible/modules/cloud/alicloud/_alicloud_ess_group.py
lib/ansible/modules/cloud/alicloud/_alicloud_ess_instance.py
lib/ansible/modules/cloud/alicloud/_alicloud_ess_rule.py
lib/ansible/modules/cloud/alicloud/_alicloud_ess_task.py
lib/ansible/modules/cloud/alicloud/_alicloud_instance.py
lib/ansible/modules/cloud/alicloud/_alicloud_instance_facts.py
lib/ansible_alicloud.egg-info/PKG-INFO
lib/ansible_alicloud.egg-info/SOURCES.txt
lib/ansible_alicloud.egg-info/dependency_links.txt
lib/ansible_alicloud.egg-info/requires.txt
lib/ansible_alicloud.egg-info/top_level.txt