Metadata-Version: 2.1
Name: ansible-alicloud
Version: 1.20.0
Summary: Ansible provider for Alicloud.
Home-page: https://github.com/alibaba/ansible-provider/tree/master/lib/ansible
Author: xiaozhu
Author-email: heguimin36@163.com
License: MIT
Classifier: Development Status :: 3 - Alpha
Classifier: Intended Audience :: Developers
Classifier: Topic :: Software Development :: Build Tools
Classifier: License :: OSI Approved :: MIT License
Classifier: Programming Language :: Python :: 3
Classifier: Programming Language :: Python :: 3.6
License-File: LICENSE
